pbx_gs_python_utils/Update_Lambda_Functions.py
pbx_gs_python_utils/__init__.py
pbx_gs_python_utils/api_jira/__init__.py
pbx_gs_python_utils/gs/__init__.py
pbx_gs_python_utils/gs_elk/__init__.py
pbx_gs_python_utils/gsbot/Slack_Commands.py
pbx_gs_python_utils/gsbot/__init__.py
pbx_gs_python_utils/lambdas/__init__.py
pbx_gs_python_utils/lambdas/api_gateway/__init__.py
pbx_gs_python_utils/lambdas/api_gateway/simple_test.py
pbx_gs_python_utils/lambdas/api_gateway/trigger_server_reload.py
pbx_gs_python_utils/lambdas/api_gateway/trigger_sync_jira_sheets.py
pbx_gs_python_utils/lambdas/dev/__init__.py
pbx_gs_python_utils/lambdas/dev/hello_world.py
pbx_gs_python_utils/lambdas/gs/__init__.py
pbx_gs_python_utils/lambdas/gsbot/__init__.py
pbx_gs_python_utils/lambdas/gsbot/gsbot_slack.py
pbx_gs_python_utils/lambdas/gsbot/build/__init__.py
pbx_gs_python_utils/lambdas/gsbot/build/trigger_build.py
pbx_gs_python_utils/lambdas/utils/__init__.py
pbx_gs_python_utils/lambdas/utils/dot_to_png.py
pbx_gs_python_utils/lambdas/utils/dot_to_slack.py
pbx_gs_python_utils/lambdas/utils/dot_to_svg.py
pbx_gs_python_utils/lambdas/utils/log_to_elk.py
pbx_gs_python_utils/lambdas/utils/pdf_to_slack.py
pbx_gs_python_utils/lambdas/utils/png_to_slack.py
pbx_gs_python_utils/lambdas/utils/puml_to_png.py
pbx_gs_python_utils/lambdas/utils/puml_to_slack.py
pbx_gs_python_utils/lambdas/utils/slack_dialog.py
pbx_gs_python_utils/lambdas/utils/slack_message.py
pbx_gs_python_utils/lambdas/utils/svg_to_png.py
pbx_gs_python_utils/plantuml/API_Plant_UML.py
pbx_gs_python_utils/plantuml/Puml.py
pbx_gs_python_utils/plantuml/Puml_Table.py
pbx_gs_python_utils/plantuml/__init__.py
pbx_gs_python_utils/utils/Assert.py
pbx_gs_python_utils/utils/Dev.py
pbx_gs_python_utils/utils/Elastic_Search.py
pbx_gs_python_utils/utils/Files.py
pbx_gs_python_utils/utils/Http.py
pbx_gs_python_utils/utils/Json.py
pbx_gs_python_utils/utils/Lambdas_Helpers.py
pbx_gs_python_utils/utils/Lists.py
pbx_gs_python_utils/utils/Local_Cache.py
pbx_gs_python_utils-0.5.1.dist-info/LICENSE
pbx_gs_python_utils-0.5.1.dist-info/METADATA
pbx_gs_python_utils-0.5.1.dist-info/WHEEL
pbx_gs_python_utils-0.5.1.dist-info/top_level.txt
pbx_gs_python_utils-0.5.1.dist-info/RECORD
