Metadata-Version: 2.1
Name: pbx-gs-python-utils
Version: 0.5.1
Summary: PBX GS Python Utils
Home-page: https://github.com/pbx-gs/pbx-gs-python-utils
Author: Dinis Cruz
Author-email: dinis.cruz@owasp.org
License: UNKNOWN
Platform: UNKNOWN
Classifier: Programming Language :: Python :: 3
Classifier: License :: OSI Approved :: MIT License
Classifier: Operating System :: OS Independent
Requires-Dist: boto3
Requires-Dist: elasticsearch
Requires-Dist: matplotlib
Requires-Dist: osbot-aws
Requires-Dist: requests
Requires-Dist: slackclient
